gempaterkini/__init__.py
latestearthquake_indonesia_sokawera-0.0.14.dist-info/LICENSE
latestearthquake_indonesia_sokawera-0.0.14.dist-info/METADATA
latestearthquake_indonesia_sokawera-0.0.14.dist-info/WHEEL
latestearthquake_indonesia_sokawera-0.0.14.dist-info/top_level.txt
latestearthquake_indonesia_sokawera-0.0.14.dist-info/RECORD
