Metadata-Version: 2.1
Name: latestearthquake-indonesia-sokawera
Version: 0.0.14
Summary: This package will get the latest earthquake from BMKG | Meteorological, Climatological, and Geophysical Agency
Home-page: https://prianthon.web.id/
Author: Pri Anton Subardio
Author-email: prianthonsubardiodanhugo@gmail.com
Project-URL: Documentation, https://github.com/prianthonhugo/latest-indonesia-earthquake/wiki
Project-URL: Bug Tracker, https://github.com/prianthonhugo/latest-indonesia-earthquake/issues
Project-URL: Source Code, https://github.com/prianthonhugo/latest-indonesia-earthquake
Classifier: Intended Audience :: Developers
Classifier: Topic :: Software Development :: Libraries :: Python Modules
Classifier: Programming Language :: Python :: 3
Classifier: License :: OSI Approved :: GNU General Public License v3 (GPLv3)
Classifier: Operating System :: OS Independent
Classifier: Development Status :: 5 - Production/Stable
License-File: LICENSE
Requires-Dist: requests
Requires-Dist: beautifulsoup4
